COPYRIGHT.txt
LICENSE.txt
README.txt
setup.py
bin/googlepagerank
tl/__init__.py
tl.googlepagerank.egg-info/PKG-INFO
tl.googlepagerank.egg-info/SOURCES.txt
tl.googlepagerank.egg-info/dependency_links.txt
tl.googlepagerank.egg-info/namespace_packages.txt
tl.googlepagerank.egg-info/top_level.txt
tl/googlepagerank/__init__.py
tl/googlepagerank/interface.py
