Metadata-Version: 1.1
Name: tl.googlepagerank
Version: 0.1
Summary: Access to Google page ranks similar to what the Google toolbar does.
Home-page: http://www.thomas-lotze.de/en/software/
Author: Thomas Lotze
Author-email: thomas@thomas-lotze.de
License: ZPL 2.1
Platform: UNKNOWN
Provides: tl.googlepagerank
